<?xml version="1.0" encoding="UTF-8" ?>
<!DOCTYPE mapper PUBLIC "-//mybatis.org//DTD Mapper 3.0//EN" "http://mybatis.org/dtd/mybatis-3-mapper.dtd" >
<mapper namespace="com.dsw.iot.dal.PersonRegisterDoMapperExt" >
  <resultMap id="BaseResultMap" type="com.dsw.iot.model.PersonRegisterDo" >
    <!--
      WARNING - @mbggenerated
      This element is automatically generated by MyBatis Generator, do not modify.
      This element was generated on Fri Feb 09 19:02:10 CST 2018.
    -->
    <id column="id" property="id" jdbcType="INTEGER" />
    <result column="card_no" property="cardNo" jdbcType="VARCHAR" />
    <result column="card_type" property="cardType" jdbcType="VARCHAR" />
    <result column="name" property="name" jdbcType="VARCHAR" />
    <result column="extra_name" property="extraName" jdbcType="VARCHAR" />
    <result column="nick_name" property="nickName" jdbcType="VARCHAR" />
    <result column="sex" property="sex" jdbcType="VARCHAR" />
    <result column="old_name" property="oldName" jdbcType="VARCHAR" />
    <result column="birth_date" property="birthDate" jdbcType="DATE" />
    <result column="phone" property="phone" jdbcType="VARCHAR" />
    <result column="domicile_area" property="domicileArea" jdbcType="VARCHAR" />
    <result column="living_area" property="livingArea" jdbcType="VARCHAR" />
    <result column="domicile_place" property="domicilePlace" jdbcType="VARCHAR" />
    <result column="living_place" property="livingPlace" jdbcType="VARCHAR" />
    <result column="education_level" property="educationLevel" jdbcType="VARCHAR" />
    <result column="marriage_type" property="marriageType" jdbcType="VARCHAR" />
    <result column="relief" property="relief" jdbcType="VARCHAR" />
    <result column="minitary" property="minitary" jdbcType="VARCHAR" />
    <result column="height" property="height" jdbcType="VARCHAR" />
    <result column="person_lable" property="personLable" jdbcType="VARCHAR" />
    <result column="work_unit" property="workUnit" jdbcType="VARCHAR" />
    <result column="profession_type" property="professionType" jdbcType="VARCHAR" />
    <result column="nationality" property="nationality" jdbcType="VARCHAR" />
    <result column="minority" property="minority" jdbcType="VARCHAR" />
    <result column="political" property="political" jdbcType="VARCHAR" />
    <result column="person_type" property="personType" jdbcType="VARCHAR" />
    <result column="unknown_person" property="unknownPerson" jdbcType="VARCHAR" />
    <result column="finger_no" property="fingerNo" jdbcType="VARCHAR" />
    <result column="DNA_no" property="dnaNo" jdbcType="VARCHAR" />
    <result column="in_type" property="inType" jdbcType="VARCHAR" />
    <result column="handing_place" property="handingPlace" jdbcType="VARCHAR" />
    <result column="case_type" property="caseType" jdbcType="VARCHAR" />
    <result column="special_group" property="specialGroup" jdbcType="VARCHAR" />
    <result column="people_type" property="peopleType" jdbcType="VARCHAR" />
    <result column="in_time" property="inTime" jdbcType="TIMESTAMP" />
    <result column="in_reason" property="inReason" jdbcType="VARCHAR" />
    <result column="handling_area" property="handlingArea" jdbcType="VARCHAR" />
    <result column="host_police_no" property="hostPoliceNo" jdbcType="VARCHAR" />
    <result column="host_police_name" property="hostPoliceName" jdbcType="VARCHAR" />
    <result column="host_police_card_no" property="hostPoliceCardNo" jdbcType="VARCHAR" />
    <result column="join_police_no" property="joinPoliceNo" jdbcType="VARCHAR" />
    <result column="join_police_name" property="joinPoliceName" jdbcType="VARCHAR" />
    <result column="join_police_card_no" property="joinPoliceCardNo" jdbcType="VARCHAR" />
    <result column="alarm_number" property="alarmNumber" jdbcType="VARCHAR" />
    <result column="word_number" property="wordNumber" jdbcType="VARCHAR" />
    <result column="medical_history" property="medicalHistory" jdbcType="VARCHAR" />
    <result column="check_body_result" property="checkBodyResult" jdbcType="VARCHAR" />
    <result column="bracelet_no" property="braceletNo" jdbcType="VARCHAR" />
    <result column="collect_project" property="collectProject" jdbcType="VARCHAR" />
    <result column="do_check" property="doCheck" jdbcType="VARCHAR" />
    <result column="locker_no" property="lockerNo" jdbcType="VARCHAR" />
    <result column="locker_id" property="lockerId" jdbcType="INTEGER" />
    <result column="is_warned" property="isWarned" jdbcType="VARCHAR" />
    <result column="examine_sign" property="examineSign" jdbcType="VARCHAR" />
    <result column="police_sign" property="policeSign" jdbcType="VARCHAR" />
    <result column="police2_sign" property="police2Sign" jdbcType="VARCHAR" />
    <result column="witness_sign" property="witnessSign" jdbcType="VARCHAR" />
    <result column="locker_admin_sign" property="lockerAdminSign" jdbcType="VARCHAR" />
    <result column="receiver_sign" property="receiverSign" jdbcType="VARCHAR" />
    <result column="delay_hour" property="delayHour" jdbcType="VARCHAR" />
    <result column="is_delay" property="isDelay" jdbcType="VARCHAR" />
    <result column="out_time" property="outTime" jdbcType="TIMESTAMP" />
    <result column="out_reason" property="outReason" jdbcType="VARCHAR" />
    <result column="person_status" property="personStatus" jdbcType="VARCHAR" />
    <result column="is_deleted" property="isDeleted" jdbcType="VARCHAR" />
    <result column="create_time" property="createTime" jdbcType="TIMESTAMP" />
    <result column="create_user" property="createUser" jdbcType="VARCHAR" />
    <result column="update_time" property="updateTime" jdbcType="TIMESTAMP" />
    <result column="update_user" property="updateUser" jdbcType="VARCHAR" />
    <result column="remark" property="remark" jdbcType="VARCHAR" />
  </resultMap>
  <sql id="Example_Where_Clause" >
    <!--
      WARNING - @mbggenerated
      This element is automatically generated by MyBatis Generator, do not modify.
      This element was generated on Fri Feb 09 19:02:10 CST 2018.
    -->
    <where >
      <foreach collection="oredCriteria" item="criteria" separator="or" >
        <if test="criteria.valid" >
          <trim prefix="(" suffix=")" prefixOverrides="and" >
            <foreach collection="criteria.criteria" item="criterion" >
              <choose >
                <when test="criterion.noValue" >
                  and ${criterion.condition}
                </when>
                <when test="criterion.singleValue" >
                  and ${criterion.condition} #{criterion.value}
                </when>
                <when test="criterion.betweenValue" >
                  and ${criterion.condition} #{criterion.value} and #{criterion.secondValue}
                </when>
                <when test="criterion.listValue" >
                  and ${criterion.condition}
                  <foreach collection="criterion.value" item="listItem" open="(" close=")" separator="," >
                    #{listItem}
                  </foreach>
                </when>
              </choose>
            </foreach>
          </trim>
        </if>
      </foreach>
    </where>
  </sql>
  <sql id="Update_By_Example_Where_Clause" >
    <!--
      WARNING - @mbggenerated
      This element is automatically generated by MyBatis Generator, do not modify.
      This element was generated on Fri Feb 09 19:02:10 CST 2018.
    -->
    <where >
      <foreach collection="example.oredCriteria" item="criteria" separator="or" >
        <if test="criteria.valid" >
          <trim prefix="(" suffix=")" prefixOverrides="and" >
            <foreach collection="criteria.criteria" item="criterion" >
              <choose >
                <when test="criterion.noValue" >
                  and ${criterion.condition}
                </when>
                <when test="criterion.singleValue" >
                  and ${criterion.condition} #{criterion.value}
                </when>
                <when test="criterion.betweenValue" >
                  and ${criterion.condition} #{criterion.value} and #{criterion.secondValue}
                </when>
                <when test="criterion.listValue" >
                  and ${criterion.condition}
                  <foreach collection="criterion.value" item="listItem" open="(" close=")" separator="," >
                    #{listItem}
                  </foreach>
                </when>
              </choose>
            </foreach>
          </trim>
        </if>
      </foreach>
    </where>
  </sql>
  <sql id="Base_Column_List" >
    <!--
      WARNING - @mbggenerated
      This element is automatically generated by MyBatis Generator, do not modify.
      This element was generated on Fri Feb 09 19:02:10 CST 2018.
    -->
    id, card_no, card_type, name, extra_name, nick_name, sex, old_name, birth_date, phone, 
    domicile_area, living_area, domicile_place, living_place, education_level, marriage_type, 
    relief, minitary, height, person_lable, work_unit, profession_type, nationality, 
    minority, political, person_type, unknown_person, finger_no, DNA_no, in_type, handing_place, 
    case_type, special_group, people_type, in_time, in_reason, handling_area, host_police_no, 
    host_police_name, host_police_card_no, join_police_no, join_police_name, join_police_card_no, 
    alarm_number, word_number, medical_history, check_body_result, bracelet_no, collect_project, 
    do_check, locker_no, locker_id, is_warned, examine_sign, police_sign, police2_sign, 
    witness_sign, locker_admin_sign, receiver_sign, delay_hour, is_delay, out_time, out_reason, 
    person_status, is_deleted, create_time, create_user, update_time, update_user, remark
  </sql>
  <select id="selectByExample" resultMap="BaseResultMap" parameterType="com.dsw.iot.model.PersonRegisterDoExample" >
    <!--
      WARNING - @mbggenerated
      This element is automatically generated by MyBatis Generator, do not modify.
      This element was generated on Fri Feb 09 19:02:10 CST 2018.
    -->
    select
    <if test="distinct" >
      distinct
    </if>
    <include refid="Base_Column_List" />
    from person_register
    <if test="_parameter != null" >
      <include refid="Example_Where_Clause" />
    </if>
    <if test="oredCriteria.size != 0" >
      and is_deleted = 'N'
    </if>
    <if test="oredCriteria.size == 0" >
      where is_deleted = 'N'
    </if>
    <if test="orderByClause != null" >
      order by ${orderByClause}
    </if>
    <if test="pageDto != null" >
      limit ${pageDto.offset},${pageDto.pageSize}
    </if>
  </select>
  <select id="selectByPrimaryKey" resultMap="BaseResultMap" parameterType="Long" >
    <!--
      WARNING - @mbggenerated
      This element is automatically generated by MyBatis Generator, do not modify.
      This element was generated on Fri Feb 09 19:02:10 CST 2018.
    -->
    select 
    <include refid="Base_Column_List" />
    from person_register
    where id = #{id,jdbcType=INTEGER}
    and is_deleted = 'N'
  </select>
  <delete id="deleteByPrimaryKey" parameterType="Long" >
    <!--
      WARNING - @mbggenerated
      This element is automatically generated by MyBatis Generator, do not modify.
      This element was generated on Fri Feb 09 19:02:10 CST 2018.
    -->
    delete from person_register
    where id = #{id,jdbcType=INTEGER}
  </delete>
  <delete id="deleteByExample" parameterType="com.dsw.iot.model.PersonRegisterDoExample" >
    <!--
      WARNING - @mbggenerated
      This element is automatically generated by MyBatis Generator, do not modify.
      This element was generated on Fri Feb 09 19:02:10 CST 2018.
    -->
    delete from person_register
    <if test="_parameter != null" >
      <include refid="Example_Where_Clause" />
    </if>
  </delete>
  <insert id="insert" parameterType="com.dsw.iot.model.PersonRegisterDo" >
    <selectKey keyProperty="id" resultType="long" >
      select LAST_INSERT_ID()
    </selectKey>
    <!--
      WARNING - @mbggenerated
      This element is automatically generated by MyBatis Generator, do not modify.
      This element was generated on Fri Feb 09 19:02:10 CST 2018.
    -->
    insert into person_register (id, card_no, card_type, 
      name, extra_name, nick_name, 
      sex, old_name, birth_date, 
      phone, domicile_area, living_area, 
      domicile_place, living_place, education_level, 
      marriage_type, relief, minitary, 
      height, person_lable, work_unit, 
      profession_type, nationality, minority, 
      political, person_type, unknown_person, 
      finger_no, DNA_no, in_type, 
      handing_place, case_type, special_group, 
      people_type, in_time, in_reason, 
      handling_area, host_police_no, host_police_name, 
      host_police_card_no, join_police_no, join_police_name, 
      join_police_card_no, alarm_number, word_number, 
      medical_history, check_body_result, bracelet_no, 
      collect_project, do_check, locker_no, 
      locker_id, is_warned, examine_sign, 
      police_sign, police2_sign, witness_sign, 
      locker_admin_sign, receiver_sign, delay_hour, 
      is_delay, out_time, out_reason, 
      person_status, is_deleted, create_time, 
      create_user, update_time, update_user, 
      remark)
    values (#{id,jdbcType=INTEGER}, #{cardNo,jdbcType=VARCHAR}, #{cardType,jdbcType=VARCHAR}, 
      #{name,jdbcType=VARCHAR}, #{extraName,jdbcType=VARCHAR}, #{nickName,jdbcType=VARCHAR}, 
      #{sex,jdbcType=VARCHAR}, #{oldName,jdbcType=VARCHAR}, #{birthDate,jdbcType=DATE}, 
      #{phone,jdbcType=VARCHAR}, #{domicileArea,jdbcType=VARCHAR}, #{livingArea,jdbcType=VARCHAR}, 
      #{domicilePlace,jdbcType=VARCHAR}, #{livingPlace,jdbcType=VARCHAR}, #{educationLevel,jdbcType=VARCHAR}, 
      #{marriageType,jdbcType=VARCHAR}, #{relief,jdbcType=VARCHAR}, #{minitary,jdbcType=VARCHAR}, 
      #{height,jdbcType=VARCHAR}, #{personLable,jdbcType=VARCHAR}, #{workUnit,jdbcType=VARCHAR}, 
      #{professionType,jdbcType=VARCHAR}, #{nationality,jdbcType=VARCHAR}, #{minority,jdbcType=VARCHAR}, 
      #{political,jdbcType=VARCHAR}, #{personType,jdbcType=VARCHAR}, #{unknownPerson,jdbcType=VARCHAR}, 
      #{fingerNo,jdbcType=VARCHAR}, #{dnaNo,jdbcType=VARCHAR}, #{inType,jdbcType=VARCHAR}, 
      #{handingPlace,jdbcType=VARCHAR}, #{caseType,jdbcType=VARCHAR}, #{specialGroup,jdbcType=VARCHAR}, 
      #{peopleType,jdbcType=VARCHAR}, #{inTime,jdbcType=TIMESTAMP}, #{inReason,jdbcType=VARCHAR}, 
      #{handlingArea,jdbcType=VARCHAR}, #{hostPoliceNo,jdbcType=VARCHAR}, #{hostPoliceName,jdbcType=VARCHAR}, 
      #{hostPoliceCardNo,jdbcType=VARCHAR}, #{joinPoliceNo,jdbcType=VARCHAR}, #{joinPoliceName,jdbcType=VARCHAR}, 
      #{joinPoliceCardNo,jdbcType=VARCHAR}, #{alarmNumber,jdbcType=VARCHAR}, #{wordNumber,jdbcType=VARCHAR}, 
      #{medicalHistory,jdbcType=VARCHAR}, #{checkBodyResult,jdbcType=VARCHAR}, #{braceletNo,jdbcType=VARCHAR}, 
      #{collectProject,jdbcType=VARCHAR}, #{doCheck,jdbcType=VARCHAR}, #{lockerNo,jdbcType=VARCHAR}, 
      #{lockerId,jdbcType=INTEGER}, #{isWarned,jdbcType=VARCHAR}, #{examineSign,jdbcType=VARCHAR}, 
      #{policeSign,jdbcType=VARCHAR}, #{police2Sign,jdbcType=VARCHAR}, #{witnessSign,jdbcType=VARCHAR}, 
      #{lockerAdminSign,jdbcType=VARCHAR}, #{receiverSign,jdbcType=VARCHAR}, #{delayHour,jdbcType=VARCHAR}, 
      #{isDelay,jdbcType=VARCHAR}, #{outTime,jdbcType=TIMESTAMP}, #{outReason,jdbcType=VARCHAR}, 
      #{personStatus,jdbcType=VARCHAR}, #{isDeleted,jdbcType=VARCHAR}, #{createTime,jdbcType=TIMESTAMP}, 
      #{createUser,jdbcType=VARCHAR}, #{updateTime,jdbcType=TIMESTAMP}, #{updateUser,jdbcType=VARCHAR}, 
      #{remark,jdbcType=VARCHAR})
  </insert>
  <insert id="insertSelective" parameterType="com.dsw.iot.model.PersonRegisterDo" >
    <selectKey keyProperty="id" resultType="long" >
      select LAST_INSERT_ID()
    </selectKey>
    <!--
      WARNING - @mbggenerated
      This element is automatically generated by MyBatis Generator, do not modify.
      This element was generated on Fri Feb 09 19:02:10 CST 2018.
    -->
    insert into person_register
    <trim prefix="(" suffix=")" suffixOverrides="," >
      <if test="id != null" >
        id,
      </if>
      <if test="cardNo != null" >
        card_no,
      </if>
      <if test="cardType != null" >
        card_type,
      </if>
      <if test="name != null" >
        name,
      </if>
      <if test="extraName != null" >
        extra_name,
      </if>
      <if test="nickName != null" >
        nick_name,
      </if>
      <if test="sex != null" >
        sex,
      </if>
      <if test="oldName != null" >
        old_name,
      </if>
      <if test="birthDate != null" >
        birth_date,
      </if>
      <if test="phone != null" >
        phone,
      </if>
      <if test="domicileArea != null" >
        domicile_area,
      </if>
      <if test="livingArea != null" >
        living_area,
      </if>
      <if test="domicilePlace != null" >
        domicile_place,
      </if>
      <if test="livingPlace != null" >
        living_place,
      </if>
      <if test="educationLevel != null" >
        education_level,
      </if>
      <if test="marriageType != null" >
        marriage_type,
      </if>
      <if test="relief != null" >
        relief,
      </if>
      <if test="minitary != null" >
        minitary,
      </if>
      <if test="height != null" >
        height,
      </if>
      <if test="personLable != null" >
        person_lable,
      </if>
      <if test="workUnit != null" >
        work_unit,
      </if>
      <if test="professionType != null" >
        profession_type,
      </if>
      <if test="nationality != null" >
        nationality,
      </if>
      <if test="minority != null" >
        minority,
      </if>
      <if test="political != null" >
        political,
      </if>
      <if test="personType != null" >
        person_type,
      </if>
      <if test="unknownPerson != null" >
        unknown_person,
      </if>
      <if test="fingerNo != null" >
        finger_no,
      </if>
      <if test="dnaNo != null" >
        DNA_no,
      </if>
      <if test="inType != null" >
        in_type,
      </if>
      <if test="handingPlace != null" >
        handing_place,
      </if>
      <if test="caseType != null" >
        case_type,
      </if>
      <if test="specialGroup != null" >
        special_group,
      </if>
      <if test="peopleType != null" >
        people_type,
      </if>
      <if test="inTime != null" >
        in_time,
      </if>
      <if test="inReason != null" >
        in_reason,
      </if>
      <if test="handlingArea != null" >
        handling_area,
      </if>
      <if test="hostPoliceNo != null" >
        host_police_no,
      </if>
      <if test="hostPoliceName != null" >
        host_police_name,
      </if>
      <if test="hostPoliceCardNo != null" >
        host_police_card_no,
      </if>
      <if test="joinPoliceNo != null" >
        join_police_no,
      </if>
      <if test="joinPoliceName != null" >
        join_police_name,
      </if>
      <if test="joinPoliceCardNo != null" >
        join_police_card_no,
      </if>
      <if test="alarmNumber != null" >
        alarm_number,
      </if>
      <if test="wordNumber != null" >
        word_number,
      </if>
      <if test="medicalHistory != null" >
        medical_history,
      </if>
      <if test="checkBodyResult != null" >
        check_body_result,
      </if>
      <if test="braceletNo != null" >
        bracelet_no,
      </if>
      <if test="collectProject != null" >
        collect_project,
      </if>
      <if test="doCheck != null" >
        do_check,
      </if>
      <if test="lockerNo != null" >
        locker_no,
      </if>
      <if test="lockerId != null" >
        locker_id,
      </if>
      <if test="isWarned != null" >
        is_warned,
      </if>
      <if test="examineSign != null" >
        examine_sign,
      </if>
      <if test="policeSign != null" >
        police_sign,
      </if>
      <if test="police2Sign != null" >
        police2_sign,
      </if>
      <if test="witnessSign != null" >
        witness_sign,
      </if>
      <if test="lockerAdminSign != null" >
        locker_admin_sign,
      </if>
      <if test="receiverSign != null" >
        receiver_sign,
      </if>
      <if test="delayHour != null" >
        delay_hour,
      </if>
      <if test="isDelay != null" >
        is_delay,
      </if>
      <if test="outTime != null" >
        out_time,
      </if>
      <if test="outReason != null" >
        out_reason,
      </if>
      <if test="personStatus != null" >
        person_status,
      </if>
      <if test="isDeleted != null" >
        is_deleted,
      </if>
      <if test="createTime != null" >
        create_time,
      </if>
      <if test="createUser != null" >
        create_user,
      </if>
      <if test="updateTime != null" >
        update_time,
      </if>
      <if test="updateUser != null" >
        update_user,
      </if>
      <if test="remark != null" >
        remark,
      </if>
    </trim>
    <trim prefix="values (" suffix=")" suffixOverrides="," >
      <if test="id != null" >
        #{id,jdbcType=INTEGER},
      </if>
      <if test="cardNo != null" >
        #{cardNo,jdbcType=VARCHAR},
      </if>
      <if test="cardType != null" >
        #{cardType,jdbcType=VARCHAR},
      </if>
      <if test="name != null" >
        #{name,jdbcType=VARCHAR},
      </if>
      <if test="extraName != null" >
        #{extraName,jdbcType=VARCHAR},
      </if>
      <if test="nickName != null" >
        #{nickName,jdbcType=VARCHAR},
      </if>
      <if test="sex != null" >
        #{sex,jdbcType=VARCHAR},
      </if>
      <if test="oldName != null" >
        #{oldName,jdbcType=VARCHAR},
      </if>
      <if test="birthDate != null" >
        #{birthDate,jdbcType=DATE},
      </if>
      <if test="phone != null" >
        #{phone,jdbcType=VARCHAR},
      </if>
      <if test="domicileArea != null" >
        #{domicileArea,jdbcType=VARCHAR},
      </if>
      <if test="livingArea != null" >
        #{livingArea,jdbcType=VARCHAR},
      </if>
      <if test="domicilePlace != null" >
        #{domicilePlace,jdbcType=VARCHAR},
      </if>
      <if test="livingPlace != null" >
        #{livingPlace,jdbcType=VARCHAR},
      </if>
      <if test="educationLevel != null" >
        #{educationLevel,jdbcType=VARCHAR},
      </if>
      <if test="marriageType != null" >
        #{marriageType,jdbcType=VARCHAR},
      </if>
      <if test="relief != null" >
        #{relief,jdbcType=VARCHAR},
      </if>
      <if test="minitary != null" >
        #{minitary,jdbcType=VARCHAR},
      </if>
      <if test="height != null" >
        #{height,jdbcType=VARCHAR},
      </if>
      <if test="personLable != null" >
        #{personLable,jdbcType=VARCHAR},
      </if>
      <if test="workUnit != null" >
        #{workUnit,jdbcType=VARCHAR},
      </if>
      <if test="professionType != null" >
        #{professionType,jdbcType=VARCHAR},
      </if>
      <if test="nationality != null" >
        #{nationality,jdbcType=VARCHAR},
      </if>
      <if test="minority != null" >
        #{minority,jdbcType=VARCHAR},
      </if>
      <if test="political != null" >
        #{political,jdbcType=VARCHAR},
      </if>
      <if test="personType != null" >
        #{personType,jdbcType=VARCHAR},
      </if>
      <if test="unknownPerson != null" >
        #{unknownPerson,jdbcType=VARCHAR},
      </if>
      <if test="fingerNo != null" >
        #{fingerNo,jdbcType=VARCHAR},
      </if>
      <if test="dnaNo != null" >
        #{dnaNo,jdbcType=VARCHAR},
      </if>
      <if test="inType != null" >
        #{inType,jdbcType=VARCHAR},
      </if>
      <if test="handingPlace != null" >
        #{handingPlace,jdbcType=VARCHAR},
      </if>
      <if test="caseType != null" >
        #{caseType,jdbcType=VARCHAR},
      </if>
      <if test="specialGroup != null" >
        #{specialGroup,jdbcType=VARCHAR},
      </if>
      <if test="peopleType != null" >
        #{peopleType,jdbcType=VARCHAR},
      </if>
      <if test="inTime != null" >
        #{inTime,jdbcType=TIMESTAMP},
      </if>
      <if test="inReason != null" >
        #{inReason,jdbcType=VARCHAR},
      </if>
      <if test="handlingArea != null" >
        #{handlingArea,jdbcType=VARCHAR},
      </if>
      <if test="hostPoliceNo != null" >
        #{hostPoliceNo,jdbcType=VARCHAR},
      </if>
      <if test="hostPoliceName != null" >
        #{hostPoliceName,jdbcType=VARCHAR},
      </if>
      <if test="hostPoliceCardNo != null" >
        #{hostPoliceCardNo,jdbcType=VARCHAR},
      </if>
      <if test="joinPoliceNo != null" >
        #{joinPoliceNo,jdbcType=VARCHAR},
      </if>
      <if test="joinPoliceName != null" >
        #{joinPoliceName,jdbcType=VARCHAR},
      </if>
      <if test="joinPoliceCardNo != null" >
        #{joinPoliceCardNo,jdbcType=VARCHAR},
      </if>
      <if test="alarmNumber != null" >
        #{alarmNumber,jdbcType=VARCHAR},
      </if>
      <if test="wordNumber != null" >
        #{wordNumber,jdbcType=VARCHAR},
      </if>
      <if test="medicalHistory != null" >
        #{medicalHistory,jdbcType=VARCHAR},
      </if>
      <if test="checkBodyResult != null" >
        #{checkBodyResult,jdbcType=VARCHAR},
      </if>
      <if test="braceletNo != null" >
        #{braceletNo,jdbcType=VARCHAR},
      </if>
      <if test="collectProject != null" >
        #{collectProject,jdbcType=VARCHAR},
      </if>
      <if test="doCheck != null" >
        #{doCheck,jdbcType=VARCHAR},
      </if>
      <if test="lockerNo != null" >
        #{lockerNo,jdbcType=VARCHAR},
      </if>
      <if test="lockerId != null" >
        #{lockerId,jdbcType=INTEGER},
      </if>
      <if test="isWarned != null" >
        #{isWarned,jdbcType=VARCHAR},
      </if>
      <if test="examineSign != null" >
        #{examineSign,jdbcType=VARCHAR},
      </if>
      <if test="policeSign != null" >
        #{policeSign,jdbcType=VARCHAR},
      </if>
      <if test="police2Sign != null" >
        #{police2Sign,jdbcType=VARCHAR},
      </if>
      <if test="witnessSign != null" >
        #{witnessSign,jdbcType=VARCHAR},
      </if>
      <if test="lockerAdminSign != null" >
        #{lockerAdminSign,jdbcType=VARCHAR},
      </if>
      <if test="receiverSign != null" >
        #{receiverSign,jdbcType=VARCHAR},
      </if>
      <if test="delayHour != null" >
        #{delayHour,jdbcType=VARCHAR},
      </if>
      <if test="isDelay != null" >
        #{isDelay,jdbcType=VARCHAR},
      </if>
      <if test="outTime != null" >
        #{outTime,jdbcType=TIMESTAMP},
      </if>
      <if test="outReason != null" >
        #{outReason,jdbcType=VARCHAR},
      </if>
      <if test="personStatus != null" >
        #{personStatus,jdbcType=VARCHAR},
      </if>
      <if test="isDeleted != null" >
        #{isDeleted,jdbcType=VARCHAR},
      </if>
      <if test="createTime != null" >
        #{createTime,jdbcType=TIMESTAMP},
      </if>
      <if test="createUser != null" >
        #{createUser,jdbcType=VARCHAR},
      </if>
      <if test="updateTime != null" >
        #{updateTime,jdbcType=TIMESTAMP},
      </if>
      <if test="updateUser != null" >
        #{updateUser,jdbcType=VARCHAR},
      </if>
      <if test="remark != null" >
        #{remark,jdbcType=VARCHAR},
      </if>
    </trim>
  </insert>
  <select id="countByExample" parameterType="com.dsw.iot.model.PersonRegisterDoExample" resultType="java.lang.Integer" >
    <!--
      WARNING - @mbggenerated
      This element is automatically generated by MyBatis Generator, do not modify.
      This element was generated on Fri Feb 09 19:02:10 CST 2018.
    -->
    select count(*) from person_register
    <if test="_parameter != null" >
      <include refid="Example_Where_Clause" />
    </if>
    <if test="oredCriteria.size != 0" >
      and is_deleted = 'N'
    </if>
    <if test="oredCriteria.size == 0" >
      where is_deleted = 'N'
    </if>
  </select>
  <update id="updateByExampleSelective" parameterType="map" >
    <!--
      WARNING - @mbggenerated
      This element is automatically generated by MyBatis Generator, do not modify.
      This element was generated on Fri Feb 09 19:02:10 CST 2018.
    -->
    update person_register
    <set >
      <if test="record.id != null" >
        id = #{record.id,jdbcType=INTEGER},
      </if>
      <if test="record.cardNo != null" >
        card_no = #{record.cardNo,jdbcType=VARCHAR},
      </if>
      <if test="record.cardType != null" >
        card_type = #{record.cardType,jdbcType=VARCHAR},
      </if>
      <if test="record.name != null" >
        name = #{record.name,jdbcType=VARCHAR},
      </if>
      <if test="record.extraName != null" >
        extra_name = #{record.extraName,jdbcType=VARCHAR},
      </if>
      <if test="record.nickName != null" >
        nick_name = #{record.nickName,jdbcType=VARCHAR},
      </if>
      <if test="record.sex != null" >
        sex = #{record.sex,jdbcType=VARCHAR},
      </if>
      <if test="record.oldName != null" >
        old_name = #{record.oldName,jdbcType=VARCHAR},
      </if>
      <if test="record.birthDate != null" >
        birth_date = #{record.birthDate,jdbcType=DATE},
      </if>
      <if test="record.phone != null" >
        phone = #{record.phone,jdbcType=VARCHAR},
      </if>
      <if test="record.domicileArea != null" >
        domicile_area = #{record.domicileArea,jdbcType=VARCHAR},
      </if>
      <if test="record.livingArea != null" >
        living_area = #{record.livingArea,jdbcType=VARCHAR},
      </if>
      <if test="record.domicilePlace != null" >
        domicile_place = #{record.domicilePlace,jdbcType=VARCHAR},
      </if>
      <if test="record.livingPlace != null" >
        living_place = #{record.livingPlace,jdbcType=VARCHAR},
      </if>
      <if test="record.educationLevel != null" >
        education_level = #{record.educationLevel,jdbcType=VARCHAR},
      </if>
      <if test="record.marriageType != null" >
        marriage_type = #{record.marriageType,jdbcType=VARCHAR},
      </if>
      <if test="record.relief != null" >
        relief = #{record.relief,jdbcType=VARCHAR},
      </if>
      <if test="record.minitary != null" >
        minitary = #{record.minitary,jdbcType=VARCHAR},
      </if>
      <if test="record.height != null" >
        height = #{record.height,jdbcType=VARCHAR},
      </if>
      <if test="record.personLable != null" >
        person_lable = #{record.personLable,jdbcType=VARCHAR},
      </if>
      <if test="record.workUnit != null" >
        work_unit = #{record.workUnit,jdbcType=VARCHAR},
      </if>
      <if test="record.professionType != null" >
        profession_type = #{record.professionType,jdbcType=VARCHAR},
      </if>
      <if test="record.nationality != null" >
        nationality = #{record.nationality,jdbcType=VARCHAR},
      </if>
      <if test="record.minority != null" >
        minority = #{record.minority,jdbcType=VARCHAR},
      </if>
      <if test="record.political != null" >
        political = #{record.political,jdbcType=VARCHAR},
      </if>
      <if test="record.personType != null" >
        person_type = #{record.personType,jdbcType=VARCHAR},
      </if>
      <if test="record.unknownPerson != null" >
        unknown_person = #{record.unknownPerson,jdbcType=VARCHAR},
      </if>
      <if test="record.fingerNo != null" >
        finger_no = #{record.fingerNo,jdbcType=VARCHAR},
      </if>
      <if test="record.dnaNo != null" >
        DNA_no = #{record.dnaNo,jdbcType=VARCHAR},
      </if>
      <if test="record.inType != null" >
        in_type = #{record.inType,jdbcType=VARCHAR},
      </if>
      <if test="record.handingPlace != null" >
        handing_place = #{record.handingPlace,jdbcType=VARCHAR},
      </if>
      <if test="record.caseType != null" >
        case_type = #{record.caseType,jdbcType=VARCHAR},
      </if>
      <if test="record.specialGroup != null" >
        special_group = #{record.specialGroup,jdbcType=VARCHAR},
      </if>
      <if test="record.peopleType != null" >
        people_type = #{record.peopleType,jdbcType=VARCHAR},
      </if>
      <if test="record.inTime != null" >
        in_time = #{record.inTime,jdbcType=TIMESTAMP},
      </if>
      <if test="record.inReason != null" >
        in_reason = #{record.inReason,jdbcType=VARCHAR},
      </if>
      <if test="record.handlingArea != null" >
        handling_area = #{record.handlingArea,jdbcType=VARCHAR},
      </if>
      <if test="record.hostPoliceNo != null" >
        host_police_no = #{record.hostPoliceNo,jdbcType=VARCHAR},
      </if>
      <if test="record.hostPoliceName != null" >
        host_police_name = #{record.hostPoliceName,jdbcType=VARCHAR},
      </if>
      <if test="record.hostPoliceCardNo != null" >
        host_police_card_no = #{record.hostPoliceCardNo,jdbcType=VARCHAR},
      </if>
      <if test="record.joinPoliceNo != null" >
        join_police_no = #{record.joinPoliceNo,jdbcType=VARCHAR},
      </if>
      <if test="record.joinPoliceName != null" >
        join_police_name = #{record.joinPoliceName,jdbcType=VARCHAR},
      </if>
      <if test="record.joinPoliceCardNo != null" >
        join_police_card_no = #{record.joinPoliceCardNo,jdbcType=VARCHAR},
      </if>
      <if test="record.alarmNumber != null" >
        alarm_number = #{record.alarmNumber,jdbcType=VARCHAR},
      </if>
      <if test="record.wordNumber != null" >
        word_number = #{record.wordNumber,jdbcType=VARCHAR},
      </if>
      <if test="record.medicalHistory != null" >
        medical_history = #{record.medicalHistory,jdbcType=VARCHAR},
      </if>
      <if test="record.checkBodyResult != null" >
        check_body_result = #{record.checkBodyResult,jdbcType=VARCHAR},
      </if>
      <if test="record.braceletNo != null" >
        bracelet_no = #{record.braceletNo,jdbcType=VARCHAR},
      </if>
      <if test="record.collectProject != null" >
        collect_project = #{record.collectProject,jdbcType=VARCHAR},
      </if>
      <if test="record.doCheck != null" >
        do_check = #{record.doCheck,jdbcType=VARCHAR},
      </if>
      <if test="record.lockerNo != null" >
        locker_no = #{record.lockerNo,jdbcType=VARCHAR},
      </if>
      <if test="record.lockerId != null" >
        locker_id = #{record.lockerId,jdbcType=INTEGER},
      </if>
      <if test="record.isWarned != null" >
        is_warned = #{record.isWarned,jdbcType=VARCHAR},
      </if>
      <if test="record.examineSign != null" >
        examine_sign = #{record.examineSign,jdbcType=VARCHAR},
      </if>
      <if test="record.policeSign != null" >
        police_sign = #{record.policeSign,jdbcType=VARCHAR},
      </if>
      <if test="record.police2Sign != null" >
        police2_sign = #{record.police2Sign,jdbcType=VARCHAR},
      </if>
      <if test="record.witnessSign != null" >
        witness_sign = #{record.witnessSign,jdbcType=VARCHAR},
      </if>
      <if test="record.lockerAdminSign != null" >
        locker_admin_sign = #{record.lockerAdminSign,jdbcType=VARCHAR},
      </if>
      <if test="record.receiverSign != null" >
        receiver_sign = #{record.receiverSign,jdbcType=VARCHAR},
      </if>
      <if test="record.delayHour != null" >
        delay_hour = #{record.delayHour,jdbcType=VARCHAR},
      </if>
      <if test="record.isDelay != null" >
        is_delay = #{record.isDelay,jdbcType=VARCHAR},
      </if>
      <if test="record.outTime != null" >
        out_time = #{record.outTime,jdbcType=TIMESTAMP},
      </if>
      <if test="record.outReason != null" >
        out_reason = #{record.outReason,jdbcType=VARCHAR},
      </if>
      <if test="record.personStatus != null" >
        person_status = #{record.personStatus,jdbcType=VARCHAR},
      </if>
      <if test="record.isDeleted != null" >
        is_deleted = #{record.isDeleted,jdbcType=VARCHAR},
      </if>
      <if test="record.createTime != null" >
        create_time = #{record.createTime,jdbcType=TIMESTAMP},
      </if>
      <if test="record.createUser != null" >
        create_user = #{record.createUser,jdbcType=VARCHAR},
      </if>
      <if test="record.updateTime != null" >
        update_time = #{record.updateTime,jdbcType=TIMESTAMP},
      </if>
      <if test="record.updateUser != null" >
        update_user = #{record.updateUser,jdbcType=VARCHAR},
      </if>
      <if test="record.remark != null" >
        remark = #{record.remark,jdbcType=VARCHAR},
      </if>
    </set>
    <if test="_parameter != null" >
      <include refid="Update_By_Example_Where_Clause" />
    </if>
  </update>
  <update id="updateByExample" parameterType="map" >
    <!--
      WARNING - @mbggenerated
      This element is automatically generated by MyBatis Generator, do not modify.
      This element was generated on Fri Feb 09 19:02:10 CST 2018.
    -->
    update person_register
    set id = #{record.id,jdbcType=INTEGER},
      card_no = #{record.cardNo,jdbcType=VARCHAR},
      card_type = #{record.cardType,jdbcType=VARCHAR},
      name = #{record.name,jdbcType=VARCHAR},
      extra_name = #{record.extraName,jdbcType=VARCHAR},
      nick_name = #{record.nickName,jdbcType=VARCHAR},
      sex = #{record.sex,jdbcType=VARCHAR},
      old_name = #{record.oldName,jdbcType=VARCHAR},
      birth_date = #{record.birthDate,jdbcType=DATE},
      phone = #{record.phone,jdbcType=VARCHAR},
      domicile_area = #{record.domicileArea,jdbcType=VARCHAR},
      living_area = #{record.livingArea,jdbcType=VARCHAR},
      domicile_place = #{record.domicilePlace,jdbcType=VARCHAR},
      living_place = #{record.livingPlace,jdbcType=VARCHAR},
      education_level = #{record.educationLevel,jdbcType=VARCHAR},
      marriage_type = #{record.marriageType,jdbcType=VARCHAR},
      relief = #{record.relief,jdbcType=VARCHAR},
      minitary = #{record.minitary,jdbcType=VARCHAR},
      height = #{record.height,jdbcType=VARCHAR},
      person_lable = #{record.personLable,jdbcType=VARCHAR},
      work_unit = #{record.workUnit,jdbcType=VARCHAR},
      profession_type = #{record.professionType,jdbcType=VARCHAR},
      nationality = #{record.nationality,jdbcType=VARCHAR},
      minority = #{record.minority,jdbcType=VARCHAR},
      political = #{record.political,jdbcType=VARCHAR},
      person_type = #{record.personType,jdbcType=VARCHAR},
      unknown_person = #{record.unknownPerson,jdbcType=VARCHAR},
      finger_no = #{record.fingerNo,jdbcType=VARCHAR},
      DNA_no = #{record.dnaNo,jdbcType=VARCHAR},
      in_type = #{record.inType,jdbcType=VARCHAR},
      handing_place = #{record.handingPlace,jdbcType=VARCHAR},
      case_type = #{record.caseType,jdbcType=VARCHAR},
      special_group = #{record.specialGroup,jdbcType=VARCHAR},
      people_type = #{record.peopleType,jdbcType=VARCHAR},
      in_time = #{record.inTime,jdbcType=TIMESTAMP},
      in_reason = #{record.inReason,jdbcType=VARCHAR},
      handling_area = #{record.handlingArea,jdbcType=VARCHAR},
      host_police_no = #{record.hostPoliceNo,jdbcType=VARCHAR},
      host_police_name = #{record.hostPoliceName,jdbcType=VARCHAR},
      host_police_card_no = #{record.hostPoliceCardNo,jdbcType=VARCHAR},
      join_police_no = #{record.joinPoliceNo,jdbcType=VARCHAR},
      join_police_name = #{record.joinPoliceName,jdbcType=VARCHAR},
      join_police_card_no = #{record.joinPoliceCardNo,jdbcType=VARCHAR},
      alarm_number = #{record.alarmNumber,jdbcType=VARCHAR},
      word_number = #{record.wordNumber,jdbcType=VARCHAR},
      medical_history = #{record.medicalHistory,jdbcType=VARCHAR},
      check_body_result = #{record.checkBodyResult,jdbcType=VARCHAR},
      bracelet_no = #{record.braceletNo,jdbcType=VARCHAR},
      collect_project = #{record.collectProject,jdbcType=VARCHAR},
      do_check = #{record.doCheck,jdbcType=VARCHAR},
      locker_no = #{record.lockerNo,jdbcType=VARCHAR},
      locker_id = #{record.lockerId,jdbcType=INTEGER},
      is_warned = #{record.isWarned,jdbcType=VARCHAR},
      examine_sign = #{record.examineSign,jdbcType=VARCHAR},
      police_sign = #{record.policeSign,jdbcType=VARCHAR},
      police2_sign = #{record.police2Sign,jdbcType=VARCHAR},
      witness_sign = #{record.witnessSign,jdbcType=VARCHAR},
      locker_admin_sign = #{record.lockerAdminSign,jdbcType=VARCHAR},
      receiver_sign = #{record.receiverSign,jdbcType=VARCHAR},
      delay_hour = #{record.delayHour,jdbcType=VARCHAR},
      is_delay = #{record.isDelay,jdbcType=VARCHAR},
      out_time = #{record.outTime,jdbcType=TIMESTAMP},
      out_reason = #{record.outReason,jdbcType=VARCHAR},
      person_status = #{record.personStatus,jdbcType=VARCHAR},
      is_deleted = #{record.isDeleted,jdbcType=VARCHAR},
      create_time = #{record.createTime,jdbcType=TIMESTAMP},
      create_user = #{record.createUser,jdbcType=VARCHAR},
      update_time = #{record.updateTime,jdbcType=TIMESTAMP},
      update_user = #{record.updateUser,jdbcType=VARCHAR},
      remark = #{record.remark,jdbcType=VARCHAR}
    <if test="_parameter != null" >
      <include refid="Update_By_Example_Where_Clause" />
    </if>
  </update>
  <update id="updateByPrimaryKeySelective" parameterType="com.dsw.iot.model.PersonRegisterDo" >
    <!--
      WARNING - @mbggenerated
      This element is automatically generated by MyBatis Generator, do not modify.
      This element was generated on Fri Feb 09 19:02:10 CST 2018.
    -->
    update person_register
    <set >
      <if test="cardNo != null" >
        card_no = #{cardNo,jdbcType=VARCHAR},
      </if>
      <if test="cardType != null" >
        card_type = #{cardType,jdbcType=VARCHAR},
      </if>
      <if test="name != null" >
        name = #{name,jdbcType=VARCHAR},
      </if>
      <if test="extraName != null" >
        extra_name = #{extraName,jdbcType=VARCHAR},
      </if>
      <if test="nickName != null" >
        nick_name = #{nickName,jdbcType=VARCHAR},
      </if>
      <if test="sex != null" >
        sex = #{sex,jdbcType=VARCHAR},
      </if>
      <if test="oldName != null" >
        old_name = #{oldName,jdbcType=VARCHAR},
      </if>
      <if test="birthDate != null" >
        birth_date = #{birthDate,jdbcType=DATE},
      </if>
      <if test="phone != null" >
        phone = #{phone,jdbcType=VARCHAR},
      </if>
      <if test="domicileArea != null" >
        domicile_area = #{domicileArea,jdbcType=VARCHAR},
      </if>
      <if test="livingArea != null" >
        living_area = #{livingArea,jdbcType=VARCHAR},
      </if>
      <if test="domicilePlace != null" >
        domicile_place = #{domicilePlace,jdbcType=VARCHAR},
      </if>
      <if test="livingPlace != null" >
        living_place = #{livingPlace,jdbcType=VARCHAR},
      </if>
      <if test="educationLevel != null" >
        education_level = #{educationLevel,jdbcType=VARCHAR},
      </if>
      <if test="marriageType != null" >
        marriage_type = #{marriageType,jdbcType=VARCHAR},
      </if>
      <if test="relief != null" >
        relief = #{relief,jdbcType=VARCHAR},
      </if>
      <if test="minitary != null" >
        minitary = #{minitary,jdbcType=VARCHAR},
      </if>
      <if test="height != null" >
        height = #{height,jdbcType=VARCHAR},
      </if>
      <if test="personLable != null" >
        person_lable = #{personLable,jdbcType=VARCHAR},
      </if>
      <if test="workUnit != null" >
        work_unit = #{workUnit,jdbcType=VARCHAR},
      </if>
      <if test="professionType != null" >
        profession_type = #{professionType,jdbcType=VARCHAR},
      </if>
      <if test="nationality != null" >
        nationality = #{nationality,jdbcType=VARCHAR},
      </if>
      <if test="minority != null" >
        minority = #{minority,jdbcType=VARCHAR},
      </if>
      <if test="political != null" >
        political = #{political,jdbcType=VARCHAR},
      </if>
      <if test="personType != null" >
        person_type = #{personType,jdbcType=VARCHAR},
      </if>
      <if test="unknownPerson != null" >
        unknown_person = #{unknownPerson,jdbcType=VARCHAR},
      </if>
      <if test="fingerNo != null" >
        finger_no = #{fingerNo,jdbcType=VARCHAR},
      </if>
      <if test="dnaNo != null" >
        DNA_no = #{dnaNo,jdbcType=VARCHAR},
      </if>
      <if test="inType != null" >
        in_type = #{inType,jdbcType=VARCHAR},
      </if>
      <if test="handingPlace != null" >
        handing_place = #{handingPlace,jdbcType=VARCHAR},
      </if>
      <if test="caseType != null" >
        case_type = #{caseType,jdbcType=VARCHAR},
      </if>
      <if test="specialGroup != null" >
        special_group = #{specialGroup,jdbcType=VARCHAR},
      </if>
      <if test="peopleType != null" >
        people_type = #{peopleType,jdbcType=VARCHAR},
      </if>
      <if test="inTime != null" >
        in_time = #{inTime,jdbcType=TIMESTAMP},
      </if>
      <if test="inReason != null" >
        in_reason = #{inReason,jdbcType=VARCHAR},
      </if>
      <if test="handlingArea != null" >
        handling_area = #{handlingArea,jdbcType=VARCHAR},
      </if>
      <if test="hostPoliceNo != null" >
        host_police_no = #{hostPoliceNo,jdbcType=VARCHAR},
      </if>
      <if test="hostPoliceName != null" >
        host_police_name = #{hostPoliceName,jdbcType=VARCHAR},
      </if>
      <if test="hostPoliceCardNo != null" >
        host_police_card_no = #{hostPoliceCardNo,jdbcType=VARCHAR},
      </if>
      <if test="joinPoliceNo != null" >
        join_police_no = #{joinPoliceNo,jdbcType=VARCHAR},
      </if>
      <if test="joinPoliceName != null" >
        join_police_name = #{joinPoliceName,jdbcType=VARCHAR},
      </if>
      <if test="joinPoliceCardNo != null" >
        join_police_card_no = #{joinPoliceCardNo,jdbcType=VARCHAR},
      </if>
      <if test="alarmNumber != null" >
        alarm_number = #{alarmNumber,jdbcType=VARCHAR},
      </if>
      <if test="wordNumber != null" >
        word_number = #{wordNumber,jdbcType=VARCHAR},
      </if>
      <if test="medicalHistory != null" >
        medical_history = #{medicalHistory,jdbcType=VARCHAR},
      </if>
      <if test="checkBodyResult != null" >
        check_body_result = #{checkBodyResult,jdbcType=VARCHAR},
      </if>
      <if test="braceletNo != null" >
        bracelet_no = #{braceletNo,jdbcType=VARCHAR},
      </if>
      <if test="collectProject != null" >
        collect_project = #{collectProject,jdbcType=VARCHAR},
      </if>
      <if test="doCheck != null" >
        do_check = #{doCheck,jdbcType=VARCHAR},
      </if>
      <if test="lockerNo != null" >
        locker_no = #{lockerNo,jdbcType=VARCHAR},
      </if>
      <if test="lockerId != null" >
        locker_id = #{lockerId,jdbcType=INTEGER},
      </if>
      <if test="isWarned != null" >
        is_warned = #{isWarned,jdbcType=VARCHAR},
      </if>
      <if test="examineSign != null" >
        examine_sign = #{examineSign,jdbcType=VARCHAR},
      </if>
      <if test="policeSign != null" >
        police_sign = #{policeSign,jdbcType=VARCHAR},
      </if>
      <if test="police2Sign != null" >
        police2_sign = #{police2Sign,jdbcType=VARCHAR},
      </if>
      <if test="witnessSign != null" >
        witness_sign = #{witnessSign,jdbcType=VARCHAR},
      </if>
      <if test="lockerAdminSign != null" >
        locker_admin_sign = #{lockerAdminSign,jdbcType=VARCHAR},
      </if>
      <if test="receiverSign != null" >
        receiver_sign = #{receiverSign,jdbcType=VARCHAR},
      </if>
      <if test="delayHour != null" >
        delay_hour = #{delayHour,jdbcType=VARCHAR},
      </if>
      <if test="isDelay != null" >
        is_delay = #{isDelay,jdbcType=VARCHAR},
      </if>
      <if test="outTime != null" >
        out_time = #{outTime,jdbcType=TIMESTAMP},
      </if>
      <if test="outReason != null" >
        out_reason = #{outReason,jdbcType=VARCHAR},
      </if>
      <if test="personStatus != null" >
        person_status = #{personStatus,jdbcType=VARCHAR},
      </if>
      <if test="isDeleted != null" >
        is_deleted = #{isDeleted,jdbcType=VARCHAR},
      </if>
      <if test="createTime != null" >
        create_time = #{createTime,jdbcType=TIMESTAMP},
      </if>
      <if test="createUser != null" >
        create_user = #{createUser,jdbcType=VARCHAR},
      </if>
      <if test="updateTime != null" >
        update_time = #{updateTime,jdbcType=TIMESTAMP},
      </if>
      <if test="updateUser != null" >
        update_user = #{updateUser,jdbcType=VARCHAR},
      </if>
      <if test="remark != null" >
        remark = #{remark,jdbcType=VARCHAR},
      </if>
    </set>
    where id = #{id,jdbcType=INTEGER}
    and is_deleted = 'N'
  </update>
  <update id="updateByPrimaryKey" parameterType="com.dsw.iot.model.PersonRegisterDo" >
    <!--
      WARNING - @mbggenerated
      This element is automatically generated by MyBatis Generator, do not modify.
      This element was generated on Fri Feb 09 19:02:10 CST 2018.
    -->
    update person_register
    set card_no = #{cardNo,jdbcType=VARCHAR},
      card_type = #{cardType,jdbcType=VARCHAR},
      name = #{name,jdbcType=VARCHAR},
      extra_name = #{extraName,jdbcType=VARCHAR},
      nick_name = #{nickName,jdbcType=VARCHAR},
      sex = #{sex,jdbcType=VARCHAR},
      old_name = #{oldName,jdbcType=VARCHAR},
      birth_date = #{birthDate,jdbcType=DATE},
      phone = #{phone,jdbcType=VARCHAR},
      domicile_area = #{domicileArea,jdbcType=VARCHAR},
      living_area = #{livingArea,jdbcType=VARCHAR},
      domicile_place = #{domicilePlace,jdbcType=VARCHAR},
      living_place = #{livingPlace,jdbcType=VARCHAR},
      education_level = #{educationLevel,jdbcType=VARCHAR},
      marriage_type = #{marriageType,jdbcType=VARCHAR},
      relief = #{relief,jdbcType=VARCHAR},
      minitary = #{minitary,jdbcType=VARCHAR},
      height = #{height,jdbcType=VARCHAR},
      person_lable = #{personLable,jdbcType=VARCHAR},
      work_unit = #{workUnit,jdbcType=VARCHAR},
      profession_type = #{professionType,jdbcType=VARCHAR},
      nationality = #{nationality,jdbcType=VARCHAR},
      minority = #{minority,jdbcType=VARCHAR},
      political = #{political,jdbcType=VARCHAR},
      person_type = #{personType,jdbcType=VARCHAR},
      unknown_person = #{unknownPerson,jdbcType=VARCHAR},
      finger_no = #{fingerNo,jdbcType=VARCHAR},
      DNA_no = #{dnaNo,jdbcType=VARCHAR},
      in_type = #{inType,jdbcType=VARCHAR},
      handing_place = #{handingPlace,jdbcType=VARCHAR},
      case_type = #{caseType,jdbcType=VARCHAR},
      special_group = #{specialGroup,jdbcType=VARCHAR},
      people_type = #{peopleType,jdbcType=VARCHAR},
      in_time = #{inTime,jdbcType=TIMESTAMP},
      in_reason = #{inReason,jdbcType=VARCHAR},
      handling_area = #{handlingArea,jdbcType=VARCHAR},
      host_police_no = #{hostPoliceNo,jdbcType=VARCHAR},
      host_police_name = #{hostPoliceName,jdbcType=VARCHAR},
      host_police_card_no = #{hostPoliceCardNo,jdbcType=VARCHAR},
      join_police_no = #{joinPoliceNo,jdbcType=VARCHAR},
      join_police_name = #{joinPoliceName,jdbcType=VARCHAR},
      join_police_card_no = #{joinPoliceCardNo,jdbcType=VARCHAR},
      alarm_number = #{alarmNumber,jdbcType=VARCHAR},
      word_number = #{wordNumber,jdbcType=VARCHAR},
      medical_history = #{medicalHistory,jdbcType=VARCHAR},
      check_body_result = #{checkBodyResult,jdbcType=VARCHAR},
      bracelet_no = #{braceletNo,jdbcType=VARCHAR},
      collect_project = #{collectProject,jdbcType=VARCHAR},
      do_check = #{doCheck,jdbcType=VARCHAR},
      locker_no = #{lockerNo,jdbcType=VARCHAR},
      locker_id = #{lockerId,jdbcType=INTEGER},
      is_warned = #{isWarned,jdbcType=VARCHAR},
      examine_sign = #{examineSign,jdbcType=VARCHAR},
      police_sign = #{policeSign,jdbcType=VARCHAR},
      police2_sign = #{police2Sign,jdbcType=VARCHAR},
      witness_sign = #{witnessSign,jdbcType=VARCHAR},
      locker_admin_sign = #{lockerAdminSign,jdbcType=VARCHAR},
      receiver_sign = #{receiverSign,jdbcType=VARCHAR},
      delay_hour = #{delayHour,jdbcType=VARCHAR},
      is_delay = #{isDelay,jdbcType=VARCHAR},
      out_time = #{outTime,jdbcType=TIMESTAMP},
      out_reason = #{outReason,jdbcType=VARCHAR},
      person_status = #{personStatus,jdbcType=VARCHAR},
      is_deleted = #{isDeleted,jdbcType=VARCHAR},
      create_time = #{createTime,jdbcType=TIMESTAMP},
      create_user = #{createUser,jdbcType=VARCHAR},
      update_time = #{updateTime,jdbcType=TIMESTAMP},
      update_user = #{updateUser,jdbcType=VARCHAR},
      remark = #{remark,jdbcType=VARCHAR}
    where id = #{id,jdbcType=INTEGER}
    and is_deleted = 'N'
  </update>
</mapper>